Metadata-Version: 1.2
Name: grvlms-stripe
Version: 1.0.1
Summary: Stripe plugin for Grvlms
Home-page: https://github.com/groovetch/grvlms-stripe
Author: GrooveTechnology
License: AGPLv3
Project-URL: Code, https://github.com/groovetch/grvlms-stripe
Project-URL: Issue tracker, https://github.com/groovetch/grvlms-stripe/issues
Platform: UNKNOWN
Classifier: Development Status :: 3 - Alpha
Classifier: Intended Audience :: Developers
Classifier: License :: OSI Approved :: GNU Affero General Public License v3
Classifier: Operating System :: OS Independent
Classifier: Programming Language :: Python
Classifier: Programming Language :: Python :: 3.5
Classifier: Programming Language :: Python :: 3.6
Classifier: Programming Language :: Python :: 3.7
Requires-Python: >=3.5
